csv_report_creator/__init__.py
csv_report_creator/__main__.py
csv_report_creator/data_loading.py
csv_report_creator/data_processing.py
csv_report_creator-0.1.0.dist-info/METADATA
csv_report_creator-0.1.0.dist-info/WHEEL
csv_report_creator-0.1.0.dist-info/top_level.txt
csv_report_creator-0.1.0.dist-info/RECORD
